setup.py
bin/dodo
dodo/__init__.py
dodo/cfg.py
dodo/connection.py
dodo.egg-info/PKG-INFO
dodo.egg-info/SOURCES.txt
dodo.egg-info/dependency_links.txt
dodo.egg-info/requires.txt
dodo.egg-info/top_level.txt