Metadata-Version: 1.1
Name: dodo
Version: 0.1.4
Summary: DigitalOcean Library and Command Line tools
Home-page: UNKNOWN
Author: Adam Wisniewski
Author-email: adamw@tbcn.ca
License: MIT
Platform: UNKNOWN
Classifier: Development Status :: 4 - Beta
Classifier: Environment :: Console
Classifier: Intended Audience :: Information Technology
Classifier: License :: OSI Approved :: MIT License
Classifier: Topic :: Software Development :: Libraries :: Python Modules
Classifier: Topic :: Utilities
